odoo/addons/website_odoo_debranding/README.rst
odoo/addons/website_odoo_debranding/__init__.py
odoo/addons/website_odoo_debranding/__manifest__.py
odoo/addons/website_odoo_debranding/hooks.py
odoo/addons/website_odoo_debranding/i18n/ca.po
odoo/addons/website_odoo_debranding/i18n/es.po
odoo/addons/website_odoo_debranding/i18n/it.po
odoo/addons/website_odoo_debranding/i18n/website_odoo_debranding.pot
odoo/addons/website_odoo_debranding/readme/CONTRIBUTORS.rst
odoo/addons/website_odoo_debranding/readme/DESCRIPTION.rst
odoo/addons/website_odoo_debranding/readme/USAGE.rst
odoo/addons/website_odoo_debranding/static/description/icon.png
odoo/addons/website_odoo_debranding/static/description/index.html
odoo/addons/website_odoo_debranding/templates/disable_odoo.xml
odoo13_addon_website_odoo_debranding-13.0.1.0.1.dev8.dist-info/METADATA
odoo13_addon_website_odoo_debranding-13.0.1.0.1.dev8.dist-info/WHEEL
odoo13_addon_website_odoo_debranding-13.0.1.0.1.dev8.dist-info/top_level.txt
odoo13_addon_website_odoo_debranding-13.0.1.0.1.dev8.dist-info/RECORD
